pygit_annek/__init__.py
pygit_annek/cli.py
pygit_annek-0.1.3.dist-info/entry_points.txt
pygit_annek-0.1.3.dist-info/LICENSE
pygit_annek-0.1.3.dist-info/WHEEL
pygit_annek-0.1.3.dist-info/METADATA
pygit_annek-0.1.3.dist-info/RECORD
