Metadata-Version: 2.1
Name: pygit-annek
Version: 0.1.3
Summary: A CLI wrapper around Pygithub
License: MIT
Author: Michael MacKenna
Author-email: mmackenna@unitedfiregroup.com
Requires-Python: >=3.8,<4.0
Classifier: License :: OSI Approved :: MIT License
Classifier: Programming Language :: Python :: 3
Classifier: Programming Language :: Python :: 3.8
Classifier: Programming Language :: Python :: 3.9
Requires-Dist: PyGithub (>=1.53,<2.0)
Requires-Dist: click (>=7.1.2,<8.0.0)
